pyc3dserver/__init__.py
pyc3dserver/pyc3dserver.py
pyc3dserver-0.3.0.dist-info/LICENSE
pyc3dserver-0.3.0.dist-info/METADATA
pyc3dserver-0.3.0.dist-info/WHEEL
pyc3dserver-0.3.0.dist-info/top_level.txt
pyc3dserver-0.3.0.dist-info/RECORD
