Metadata-Version: 2.1
Name: pyc3dserver
Version: 0.3.0
Summary: Python interface of C3Dserver software for reading and editing C3D motion capture files.
Home-page: https://github.com/mkjung99/pyc3dserver
Author: Moon Ki Jung (et al.)
Author-email: m.k.jung@outlook.com
Classifier: Programming Language :: Python :: 3
Classifier: License :: OSI Approved :: MIT License
Classifier: Operating System :: Microsoft :: Windows :: Windows 10
Classifier: Topic :: Scientific/Engineering :: Information Analysis
Classifier: Intended Audience :: Science/Research
Requires-Python: >=3.8
License-File: LICENSE
Requires-Dist: numpy>=1.24
Requires-Dist: scipy
Requires-Dist: pywin32>=223
